HISTORY.txt
MANIFEST.in
README.md
setup.cfg
setup.py
sparc/__init__.py
sparc.apps.cache.egg-info/PKG-INFO
sparc.apps.cache.egg-info/SOURCES.txt
sparc.apps.cache.egg-info/dependency_links.txt
sparc.apps.cache.egg-info/entry_points.txt
sparc.apps.cache.egg-info/namespace_packages.txt
sparc.apps.cache.egg-info/not-zip-safe
sparc.apps.cache.egg-info/requires.txt
sparc.apps.cache.egg-info/top_level.txt
sparc/apps/__init__.py
sparc/apps/cache/__init__.py
sparc/apps/cache/cache.py
sparc/apps/cache/configure.py
sparc/apps/cache/configure.zcml
sparc/apps/cache/log.py
sparc/apps/cache/sql.py
sparc/apps/cache/sample/__init__.py
sparc/apps/cache/sample/configure.zcml