Metadata-Version: 1.1
Name: sparc.apps.cache
Version: 0.0.5
Summary: A generic CSV to SQL DB caching utility.
Home-page: https://github.com/davisd50/sparc.apps.cache
Author: David Davis
Author-email: davisd50@gmail.com
License: MIT
Keywords: zca
Platform: UNKNOWN
Classifier: Development Status :: 2 - Pre-Alpha
Classifier: Intended Audience :: Developers
Classifier: License :: OSI Approved :: MIT License
Classifier: Natural Language :: English
Classifier: Programming Language :: Python :: 2
Classifier: Programming Language :: Python :: 2.7
